columnar/__init__.py
columnar/columnar.py
columnar/exceptions.py
Columnar-1.4.0.dist-info/LICENSE.txt
Columnar-1.4.0.dist-info/METADATA
Columnar-1.4.0.dist-info/WHEEL
Columnar-1.4.0.dist-info/top_level.txt
Columnar-1.4.0.dist-info/RECORD
