Metadata-Version: 2.1
Name: Columnar
Version: 1.4.0
Summary: A tool for printing data in a columnar format.
Home-page: UNKNOWN
Author: Max Taggart
Author-email: max.taggart@gmail.com
License: UNKNOWN
Platform: UNKNOWN
Classifier: Programming Language :: Python :: 3.7
Classifier: License :: OSI Approved :: MIT License
Classifier: Operating System :: OS Independent
Requires-Dist: toolz
Requires-Dist: wcwidth
